{
  "URL" : "http://www.thehindu.com/news/national/kidney-racket-five-mumbai-hospital-medicos-get-bail/article9003026.ece",
  "Title" : "Kidney racket: Five Mumbai hospital medicos get bail ",
  "Category" : [ "" ],
  "Tags" : [ "" ],
  "Content" : [ "The five doctors with the LH Hiranandani Hospital in Powai who were arrested in connection with the kidney transplant racket busted at the hospital last month, were on Thursday granted bail on a sure" ],
  "Created Date and Time" : "2016-08-18T16:35:35+05:30",
  "Modified Date andTime" : "2016-08-19T00:23:50+05:30",
  "Author" : [ "Special Correspondent" ],
  "Description" : "The five doctors with the LH Hiranandani Hospital in Powai who were arrested in connection with the kidney transplant racket busted at the hospital last month, were on Thursday granted bail on a sure",
  "section" : "National",
  "type" : "article"
}
