{
  "URL" : "http://www.thehindu.com/news/cities/Delhi/acb-raids-delhi-commission-for-women-office/article9002606.ece",
  "Title" : "ACB 'raids' Delhi Commission for Women office",
  "Category" : [ "" ],
  "Tags" : [ "" ],
  "Content" : [ "The Anti-Corruption Branch on Thursday carried out a search at Delhi Commission for Women after three complaints were filed against the women's body over appointments. Former DCW chief and Congres" ],
  "Created Date and Time" : "2016-08-18T13:02:36+05:30",
  "Modified Date andTime" : "2016-08-18T15:28:37+05:30",
  "Author" : [ "Maria Akram" ],
  "Description" : "The Anti-Corruption Branch on Thursday carried out a search at Delhi Commission for Women after three complaints were filed against the women's body over appointments. Former DCW chief and Congres",
  "section" : "Delhi",
  "type" : "article"
}
